python_can_csscan_txt/python_can_csscan_txt.so
python_can_csscan_txt/python_can_csscan_txt.pyi
python_can_csscan_txt/__init__.py
python_can_csscan_txt-2.4.0.dist-info/METADATA
python_can_csscan_txt-2.4.0.dist-info/RECORD
python_can_csscan_txt-2.4.0.dist-info/WHEEL
python_can_csscan_txt-2.4.0.dist-info/entry_points.txt
python_can_csscan_txt-2.4.0.dist-info/licenses/LICENSE
