Metadata-Version: 2.1
Name: python-can-csscan-txt
Version: 2.4.0
Summary: Extract bus logging data from TXT files generated by CLX000 from CSS Electronics
Project-URL: Homepage, https://canlogger.csselectronics.com/tools-docs/csscan_txt/python_csscan/
Author: CSS Electronics
Author-email: contact@csselectronics.com
License-File: LICENSE
Classifier: License :: OSI Approved :: MIT License
Classifier: Operating System :: OS Independent
Classifier: Programming Language :: Python :: 3
Requires-Python: >=3.7
Requires-Dist: python-can>=4.3.1
